LICENSE.txt
setup.py
Charaf_calculator.egg-info/PKG-INFO
Charaf_calculator.egg-info/SOURCES.txt
Charaf_calculator.egg-info/dependency_links.txt
Charaf_calculator.egg-info/top_level.txt
code/__init__.py