Metadata-Version: 2.1
Name: Charaf-calculator
Version: 0.1
Summary: simple library in python for test
Author: Charaf-Saaoudi
License-File: LICENSE.txt
